ausikor_common/__init__.py
ausikor_common/app/__init__.py
ausikor_common/app/exception/__init__.py
ausikor_common/app/exception/exception_handler.py
ausikor_common/app/exception/exception_wrapper.py
ausikor_common/app/health/__init__.py
ausikor_common/app/health/health_model.py
ausikor_common/app/http/__init__.py
ausikor_common/app/http/http_status_code.py
ausikor_common/app/logger/__init__.py
ausikor_common/app/logger/log.py
ausikor_common/app/logger/printer.py
ausikor_common/app/response/__init__.py
ausikor_common/app/response/response_crud_helper.py
ausikor_common/app/response/response_factory.py
ausikor_common/app/response/response_service.py
ausikor_common/app/response/response_state.py
ausikor_common/database/__init__.py
ausikor_common/database/db.py
ausikor_common/database/db_factory.py
ausikor_common/database/db_init.py
ausikor_common/database/load_env.py
ausikor_common/form/__init__.py
ausikor_common/form/form_data.py
ausikor_common/security/__init__.py
ausikor_common/security/encrypt/__init__.py
ausikor_common/security/encrypt/password_factory.py
ausikor_common/security/encrypt/uuid_factory.py
ausikor_common/security/token/__init__.py
ausikor_common/security/token/check_customer_access_token.py
ausikor_common/security/token/check_employee_access_token.py
ausikor_common/security/token/customer_token_wrapper.py
ausikor_common/security/token/employee_token_wrapper.py
ausikor_common/security/token/token_model.py
ausikor_common/security/token/verify_access_token.py
ausikor_common/security/token/verify_token_wrapper.py
ausikor_common/utils/__init__.py
ausikor_common/utils/config/__init__.py
ausikor_common/utils/config/base_config.py
ausikor_common/utils/config/dependencies.py
ausikor_common/utils/constant/__init__.py
ausikor_common/utils/constant/settings.py
ausikor_common/utils/email/__init__.py
ausikor_common/utils/email/email_model.py
ausikor_common/utils/email/email_schema.py
ausikor_common/utils/email/email_service.py
ausikor_common-0.1.9.dist-info/licenses/LICENSE
ausikor_common-0.1.9.dist-info/METADATA
ausikor_common-0.1.9.dist-info/WHEEL
ausikor_common-0.1.9.dist-info/top_level.txt
ausikor_common-0.1.9.dist-info/RECORD
