Metadata-Version: 2.4
Name: ausikor-common
Version: 0.1.9
Summary: My first common utils
Author-email: Park Jungkwan <pakjkwan@gmail.com>
Project-URL: Homepage, https://github.com/labzang/ausikor-common
Project-URL: Bug Tracker, https://github.com/labzang/ausikor-common/issues
Requires-Python: >=3.9
License-File: LICENSE
Requires-Dist: pydantic>=2.7
Requires-Dist: httpx>=0.27
Requires-Dist: python-jose[cryptography]>=3.3.0
Requires-Dist: loguru>=0.7.2
Requires-Dist: psycopg2-binary>=2.9
Requires-Dist: asyncpg>=0.29
Provides-Extra: dev
Requires-Dist: pytest; extra == "dev"
Requires-Dist: pytest-cov; extra == "dev"
Requires-Dist: ruff; extra == "dev"
Requires-Dist: mypy; extra == "dev"
Requires-Dist: build; extra == "dev"
Requires-Dist: twine; extra == "dev"
Dynamic: license-file
